irisml/tasks/evaluate_torchmetrics_classification_multiclass.py
irisml/tasks/evaluate_torchmetrics_classification_multilabel.py
irisml_tasks_torchmetrics-0.0.2.dist-info/LICENSE
irisml_tasks_torchmetrics-0.0.2.dist-info/METADATA
irisml_tasks_torchmetrics-0.0.2.dist-info/WHEEL
irisml_tasks_torchmetrics-0.0.2.dist-info/top_level.txt
irisml_tasks_torchmetrics-0.0.2.dist-info/RECORD
