Metadata-Version: 2.1
Name: irisml-tasks-torchmetrics
Version: 0.0.2
Summary: IrisML tasks for torchmetrics
Home-page: https://github.com/microsoft/irisml-tasks-torchmetrics
Author: irisdev
License: MIT
Requires-Python: >=3.8
License-File: LICENSE
Requires-Dist: irisml
Requires-Dist: torchmetrics ~=1.2.1
